mergecal/__init__.py
mergecal/__main__.py
mergecal/calendar_merger.py
mergecal/cli.py
mergecal/py.typed
mergecal-0.5.0.dist-info/LICENSE
mergecal-0.5.0.dist-info/METADATA
mergecal-0.5.0.dist-info/WHEEL
mergecal-0.5.0.dist-info/entry_points.txt
mergecal-0.5.0.dist-info/top_level.txt
mergecal-0.5.0.dist-info/RECORD
