Metadata-Version: 2.2
Name: mergecal
Version: 0.5.0
Summary: A Python library to merge iCalendar feeds.
Author-email: Abe Hanoka <abe@habet.dev>
License: GNU General Public License v3
Project-URL: Bug Tracker, https://github.com/abe-101/mergecal/issues
Project-URL: Changelog, https://github.com/abe-101/mergecal/blob/main/CHANGELOG.md
Project-URL: documentation, https://mergecal.readthedocs.io
Project-URL: repository, https://github.com/abe-101/mergecal
Classifier: Development Status :: 2 - Pre-Alpha
Classifier: Intended Audience :: Developers
Classifier: Natural Language :: English
Classifier: Operating System :: OS Independent
Classifier: Programming Language :: Python :: 3.9
Classifier: Programming Language :: Python :: 3.10
Classifier: Programming Language :: Python :: 3.11
Classifier: Programming Language :: Python :: 3.12
Classifier: Programming Language :: Python :: 3.13
Classifier: Topic :: Software Development :: Libraries
Requires-Python: >=3.9
License-File: LICENSE
Requires-Dist: icalendar>=6.1.1
Requires-Dist: rich>=10
Requires-Dist: typer<1,>=0.15
Requires-Dist: x-wr-timezone>=2.0.1
